maxborn/__init__.py
maxborn/commandline.py
maxborn/version.py
maxborn-0.0.1.dist-info/LICENSE
maxborn-0.0.1.dist-info/METADATA
maxborn-0.0.1.dist-info/WHEEL
maxborn-0.0.1.dist-info/entry_points.txt
maxborn-0.0.1.dist-info/top_level.txt
maxborn-0.0.1.dist-info/RECORD
