Metadata-Version: 2.1
Name: maxborn
Version: 0.0.1
Summary: Python visualization library for high energy physics inspired by seaborn
Home-page: https://github.com/matthewfeickert/maxborn
Author: Matthew Feickert
Author-email: matthew.feickert@cern.ch
License: Apache
Project-URL: Documentation, https://matthewfeickert.github.io/maxborn/
Project-URL: Source, https://github.com/matthewfeickert/maxborn
Project-URL: Tracker, https://github.com/matthewfeickert/maxborn/issues
Keywords: physics visualization
Platform: UNKNOWN
Classifier: Development Status :: 4 - Beta
Classifier: License :: OSI Approved :: Apache Software License
Classifier: Intended Audience :: Science/Research
Classifier: Topic :: Scientific/Engineering
Classifier: Topic :: Scientific/Engineering :: Physics
Classifier: Programming Language :: Python :: 3
Classifier: Programming Language :: Python :: 3.6
Classifier: Programming Language :: Python :: 3.7
Classifier: Programming Language :: Python :: 3.8
Requires-Python: >=3.6
Requires-Dist: click (>=6.0)
Provides-Extra: complete
Requires-Dist: black ; extra == 'complete'
Requires-Dist: bumpversion (~=0.5) ; extra == 'complete'
Requires-Dist: check-manifest ; extra == 'complete'
Requires-Dist: pre-commit ; extra == 'complete'
Requires-Dist: pyflakes ; extra == 'complete'
Requires-Dist: pytest-console-scripts (~=0.2) ; extra == 'complete'
Requires-Dist: pytest-cov (~=2.8) ; extra == 'complete'
Requires-Dist: pytest (~=5.2) ; extra == 'complete'
Requires-Dist: twine ; extra == 'complete'
Provides-Extra: develop
Requires-Dist: check-manifest ; extra == 'develop'
Requires-Dist: pytest (~=5.2) ; extra == 'develop'
Requires-Dist: pytest-cov (~=2.8) ; extra == 'develop'
Requires-Dist: pytest-console-scripts (~=0.2) ; extra == 'develop'
Requires-Dist: bumpversion (~=0.5) ; extra == 'develop'
Requires-Dist: pyflakes ; extra == 'develop'
Requires-Dist: pre-commit ; extra == 'develop'
Requires-Dist: black ; extra == 'develop'
Requires-Dist: twine ; extra == 'develop'
